{
    "name": "Children",
    "order": "created",
    "sort": "desc",
    "layout": {
        "items": [
            {
                "type": "field",
                "value": "id",
                "width": "5%",
                "sortable": false,
                "readonly": true,
                "visible": false
            },
            {
                "type": "field",
                "value": "firstname",
                "width": "20%",
                "sortable": false,
                "readonly": true
            },
            {
                "type": "field",
                "value": "lastname",
                "width": "20%",
                "sortable": false,
                "readonly": true
            },
            {
                "type": "field",
                "value": "birthdate",
                "width": "20%",
                "sortable": false,
                "readonly": true
            },
            {
                "type": "field",
                "value": "gender",
                "width": "20%",
                "sortable": false,
                "readonly": true
            },
            {
                "type": "field",
                "value": "main_guardian_id",
                "width": "20%",
                "sortable": false,
                "readonly": true
            },
            {
                "type": "field",
                "value": "institution_id",
                "width": "20%",
                "sortable": false,
                "readonly": true
            },
            {
                "type": "field",
                "value": "is_foster",
                "width": "20%",
                "sortable": false,
                "readonly": true,
                "visible": false
            }
        ]
    }
}